cs/numeric.py
cs.numeric-20220606.dist-info/METADATA
cs.numeric-20220606.dist-info/WHEEL
cs.numeric-20220606.dist-info/top_level.txt
cs.numeric-20220606.dist-info/RECORD
